reddiornaut/__init__.py
reddiornaut/fetch.py
reddiornaut/objects.py
reddiornaut-0.1.0.dist-info/LICENSE
reddiornaut-0.1.0.dist-info/METADATA
reddiornaut-0.1.0.dist-info/WHEEL
reddiornaut-0.1.0.dist-info/top_level.txt
reddiornaut-0.1.0.dist-info/RECORD
