Metadata-Version: 2.1
Name: reddiornaut
Version: 0.1.0
Summary: An async wrapper for reddit's JSON API
Home-page: https://github.com/bwmabe/reddiornaut
Author: bwmabe
Author-email: benwmabe@gmail.com
License: UNKNOWN
Project-URL: Bug Tracker, https://github.com/bwmabe/reddiornaut/issues
Platform: UNKNOWN
Classifier: Programming Language :: Python :: 3
Classifier: License :: OSI Approved :: MIT License
Classifier: Operating System :: OS Independent
Requires-Python: >=3.6
